Metadata-Version: 1.0
Name: Products.ATReferenceBrowserWidget
Version: 3.0
Summary: ATReferenceBrowserWidget is reference widget for Archetypes.
Home-page: http://pypi.python.org/pypi/Products.ATReferenceBrowserWidget
Author: Danny Bloemendaal
Author-email: plone-developers@lists.sourceforge.net
License: GPL
Keywords: CMF Plone Archetypes reference widget
Platform: UNKNOWN
Classifier: Framework :: Plone
Classifier: License :: OSI Approved :: GNU General Public License (GPL)
Classifier: Programming Language :: Python
